geotekppu/__init__.py
geotekppu/rmr/__init__.py
geotekppu/rmr/rmr__bieniawski1989.py
geotekppu/rmr/rmr__celada_etal2014.py
geotekppu/rmr/rmr__sen_sadagah2002.py
geotekppu/rmr/rmr_b_geocontrol2012.py
geotekppu/rmr/rmr_hlw_tong_etal2022.py
geotekppu/smr/__init__.py
geotekppu/smr/smr__chen1995.py
geotekppu/smr/smr__romana_ts2015.py
geotekppu/smr/smr__tomas2007.py
geotekppu-0.1.0.dist-info/LICENSE
geotekppu-0.1.0.dist-info/METADATA
geotekppu-0.1.0.dist-info/WHEEL
geotekppu-0.1.0.dist-info/top_level.txt
geotekppu-0.1.0.dist-info/RECORD
