Metadata-Version: 2.1
Name: geotekppu
Version: 0.1.0
Summary: A python module for geotechnic analysis.
Author-email: Febri Fahmi Hakim <fahmi_fafa@yahoo.com>, Daru Jaka Sasangka <darujakasasangka@gmail.com>
Project-URL: Homepage, https://github.com/febrifahmi/geotekppu
Project-URL: Bug Tracker, https://github.com/febrifahmi/geotekppu/issues
Classifier: Programming Language :: Python :: 3
Classifier: License :: OSI Approved :: MIT License
Classifier: Operating System :: OS Independent
Requires-Python: >=3.7
License-File: LICENSE
